MANIFEST.in
setup.py
docs/CHANGES.txt
docs/CONTRIBUTORS.txt
docs/README.txt
fourdigits/__init__.py
fourdigits.recipe.supervisor.egg-info/PKG-INFO
fourdigits.recipe.supervisor.egg-info/SOURCES.txt
fourdigits.recipe.supervisor.egg-info/dependency_links.txt
fourdigits.recipe.supervisor.egg-info/entry_points.txt
fourdigits.recipe.supervisor.egg-info/namespace_packages.txt
fourdigits.recipe.supervisor.egg-info/not-zip-safe
fourdigits.recipe.supervisor.egg-info/requires.txt
fourdigits.recipe.supervisor.egg-info/top_level.txt
fourdigits/recipe/__init__.py
fourdigits/recipe/supervisor/README.txt
fourdigits/recipe/supervisor/__init__.py
fourdigits/recipe/supervisor/tests/__init__.py
fourdigits/recipe/supervisor/tests/test_docs.py