Metadata-Version: 1.0
Name: fourdigits.recipe.supervisor
Version: 0.18dev
Summary: A buildout recipe to install supervisor
Home-page: http://pypi.python.org/pypi/fourdigits.recipe.supervisor
Author: Mustapha Benali
Author-email: mustapha@headnet.dk
License: ZPL
Keywords: buildout recipe supervisor
Platform: UNKNOWN
Classifier: Framework :: Buildout
Classifier: Intended Audience :: Developers
Classifier: Topic :: Software Development :: Build Tools
Classifier: Topic :: Software Development :: Libraries :: Python Modules
Classifier: License :: OSI Approved :: Zope Public License
